diffeq_solver_tk/__init__.py
diffeq_solver_tk/__main__.py
diffeq_solver_tk/cli.py
diffeq_solver_tk/excel_export.py
diffeq_solver_tk/diffeq/__init__.py
diffeq_solver_tk/diffeq/_conversion.py
diffeq_solver_tk/diffeq/_differential_equation_metadata.py
diffeq_solver_tk/diffeq/_differential_equation_service.py
diffeq_solver_tk/diffeq/_finite_difference.py
diffeq_solver_tk/ui/__init__.py
diffeq_solver_tk/ui/app.py
diffeq_solver_tk/ui/form_container.py
diffeq_solver_tk/ui/forms/__init__.py
diffeq_solver_tk/ui/forms/_differential_equation_form.py
diffeq_solver_tk/ui/forms/_first_order_ode_form.py
diffeq_solver_tk/ui/forms/_heat_equation_form.py
diffeq_solver_tk/ui/forms/_second_order_ode_form.py
diffeq_solver_tk/ui/forms/_wave_equation_form.py
diffeq_solver_tk/ui/messages/__init__.py
diffeq_solver_tk/ui/messages/_common_messages.py
diffeq_solver_tk/ui/messages/_first_order_ode_messages.py
diffeq_solver_tk/ui/messages/_heat_equation_messages.py
diffeq_solver_tk/ui/messages/_second_order_ode_messages.py
diffeq_solver_tk/ui/messages/_wave_equation_messages.py
diffeq_solver_tk-0.0.12.dist-info/LICENSE
diffeq_solver_tk-0.0.12.dist-info/METADATA
diffeq_solver_tk-0.0.12.dist-info/WHEEL
diffeq_solver_tk-0.0.12.dist-info/entry_points.txt
diffeq_solver_tk-0.0.12.dist-info/top_level.txt
diffeq_solver_tk-0.0.12.dist-info/RECORD
