Metadata-Version: 2.1
Name: diffeq_solver_tk
Version: 0.0.12
Summary: Tkinter application for solving differential equations.
Author: Joey Shi
Platform: unix
Platform: linux
Platform: osx
Platform: cygwin
Platform: win32
Classifier: Programming Language :: Python :: 3
Classifier: Programming Language :: Python :: 3 :: Only
Classifier: Programming Language :: Python :: 3.10
Requires-Python: >=3.10
License-File: LICENSE
Requires-Dist: matplotlib
Requires-Dist: openpyxl
Requires-Dist: numpy
